hafweb/__init__.py
hafweb/__main__.py
hafweb/app.py
hafweb/config.py
hafweb/error.py
hafweb/generator.py
hafweb/main.py
hafweb/controller/__init__.py
hafweb/controller/controller.py
hafweb/controller/controller_api.py
hafweb/controller/controller_app.py
hafweb/controller/controller_main.py
hafweb/controller/controller_token.py
hafweb/controller/engine.py
hafweb/controller/__pycache__/__init__.cpython-37.pyc
hafweb/controller/__pycache__/controller.cpython-37.pyc
hafweb/controller/__pycache__/controller_api.cpython-37.pyc
hafweb/controller/__pycache__/controller_main.cpython-37.pyc
hafweb/controller/__pycache__/controller_token.cpython-37.pyc
hafweb/controller/__pycache__/engine.cpython-37.pyc
hafweb/model/__init__.py
hafweb/model/model.py
hafweb/model/model_api.py
hafweb/model/model_app.py
hafweb/model/model_token.py
hafweb/model/__pycache__/__init__.cpython-37.pyc
hafweb/model/__pycache__/model.cpython-37.pyc
hafweb/model/__pycache__/model_api.cpython-37.pyc
hafweb/model/__pycache__/model_token.cpython-37.pyc
hafweb/resource/case.html
hafweb/resource/index.html
hafweb/resource/main.html
hafweb/resource/main_one.html
hafweb/resource/test.html
hafweb/resource/today.html
hafweb/resource/css/bootstrap-datepicker.css
hafweb/resource/css/bootstrap-datepicker.css.map
hafweb/resource/css/bootstrap-datepicker.min.css
hafweb/resource/css/bootstrap.min.css
hafweb/resource/css/bootstrap.min.css.map
hafweb/resource/js/base.js
hafweb/resource/js/bootstrap-datepicker.js
hafweb/resource/js/bootstrap-datepicker.min.js
hafweb/resource/js/bootstrap.min.js
hafweb/resource/js/bootstrap.min.js.map
hafweb/resource/js/echarts.min.js
hafweb/resource/js/jquery.min.js
hafweb/route/__init__.py
hafweb/route/route.py
hafweb/route/route_api.py
hafweb/route/route_token.py
hafweb/route/__pycache__/__init__.cpython-37.pyc
hafweb/route/__pycache__/route.cpython-37.pyc
hafweb/route/__pycache__/route_api.cpython-37.pyc
hafweb/route/__pycache__/route_token.cpython-37.pyc
hafweb/view/__init__.py
hafweb-0.2.3.dist-info/LICENSE
hafweb-0.2.3.dist-info/METADATA
hafweb-0.2.3.dist-info/WHEEL
hafweb-0.2.3.dist-info/top_level.txt
hafweb-0.2.3.dist-info/RECORD
